{"primary-color":"#e0006c","gradient1-start-color":"#ed2a99","heading-font":"Exo","heading-color":"#3d3d3d","heading-underline-color":"#3d3d3d","text-font":"georgia","section-header-underline-thickness":3,"section-header-letter-spacing":0,"text-color":"#888888","button-light-color":"#e0006c","button-dark-color":"#e0006c","quotes-content-font-family":"Exo","text-font2":"georgia","section-header-title-font-size":30,"header-style":"v2","preloader-enable":"show","header-v2-bg-image":"http:\/\/fashion.semona.wpengine.com\/wp-content\/uploads\/sites\/3\/2015\/07\/fashion-aboutus-breadcrumbs-bg.jpg","logo-dark":"http:\/\/fashion.semona.wpengine.com\/wp-content\/uploads\/sites\/3\/2015\/08\/logo-white.png","logo-dark-retina":"http:\/\/fashion.semona.wpengine.com\/wp-content\/uploads\/sites\/3\/2015\/08\/logo-white@2x.png","footer-style":"style4","footer-text-color":"#6e6b76","footer-bg-color":"#212026","footer-border-color":"#373643","widget-area-title-color":"#bdbdbe","footer-copyright-bg-color":"#262626","widget-area-columns":"1","footer-heading-font":"Exo","footer-text-font":"Exo","footer-copyright-font":"Exo","widget-area-padding-top":"50","widget-area-padding-bottom":"30","portfolio-show-related":"no","border-color":"#d7d7d7","portfolio-layout":"grid4","portfolio-grid-columns":"4","logo-light":"http:\/\/fashion.semona.wpengine.com\/wp-content\/uploads\/sites\/3\/2015\/08\/logo-dark.png","logo-light-retina":"http:\/\/fashion.semona.wpengine.com\/wp-content\/uploads\/sites\/3\/2015\/08\/logo-dark@2x.png","portfolio-slug":"models","nav_menu_locations":{"main-menu":5},"latest-tweet-twitter_id":"hakimjaya06","latest-tweet-consumer_key":"zX01dcqoMjEA2O9BTGJTI0FaW","latest-tweet-consumer_secret":"LmAHuB75OWaMnj53RgaZs0SL9j1TdzqJ8NMvVCZH0GTUFdxxCL","latest-tweet-access_token":"2847626113-QOOfL6Z9uye4oNdnsN3Dkhdd9YzUMZDGhO47DPV","latest-tweet-access_token_secret":"BsKE8l4wPZ4o0MBjinIWz55u1odDyNcqGNDGKbFG7xRYH"}